flyde/__init__.py
flyde/cli.py
flyde/flow.py
flyde/io.py
flyde/node.py
flyde/nodes.py
flyde/py.typed
pyflyde-0.1.0.dist-info/licenses/LICENSE
pyflyde-0.1.0.dist-info/METADATA
pyflyde-0.1.0.dist-info/WHEEL
pyflyde-0.1.0.dist-info/entry_points.txt
pyflyde-0.1.0.dist-info/top_level.txt
pyflyde-0.1.0.dist-info/RECORD
